streamlit_react_flow/__init__.py
streamlit_react_flow/frontend/build/asset-manifest.json
streamlit_react_flow/frontend/build/bootstrap.min.css
streamlit_react_flow/frontend/build/index.html
streamlit_react_flow/frontend/build/precache-manifest.d2af41252694bd35bd084ade81f6d125.js
streamlit_react_flow/frontend/build/service-worker.js
streamlit_react_flow/frontend/build/static/js/2.d9806b68.chunk.js
streamlit_react_flow/frontend/build/static/js/2.d9806b68.chunk.js.LICENSE.txt
streamlit_react_flow/frontend/build/static/js/2.d9806b68.chunk.js.map
streamlit_react_flow/frontend/build/static/js/main.ff53b4cc.chunk.js
streamlit_react_flow/frontend/build/static/js/main.ff53b4cc.chunk.js.map
streamlit_react_flow/frontend/build/static/js/runtime-main.c3ac24d1.js
streamlit_react_flow/frontend/build/static/js/runtime-main.c3ac24d1.js.map
streamlit_react_flow-0.0.3.dist-info/LICENSE
streamlit_react_flow-0.0.3.dist-info/METADATA
streamlit_react_flow-0.0.3.dist-info/WHEEL
streamlit_react_flow-0.0.3.dist-info/top_level.txt
streamlit_react_flow-0.0.3.dist-info/RECORD
